permute/__init__.py
permute/conftest.py
permute/core.py
permute/irr.py
permute/ksample.py
permute/npc.py
permute/qa.py
permute/sprt.py
permute/stratified.py
permute/utils.py
permute/data/MacNell2014.csv
permute/data/__init__.py
permute/data/nsgk.csv
permute/data/rb_clinical_trial.csv
permute/data/npc/botulinum.csv
permute/data/npc/chrom17m.csv
permute/data/npc/confocal.csv
permute/data/npc/germina.csv
permute/data/npc/kenya.csv
permute/data/npc/massaro_blair.csv
permute/data/npc/monachus.csv
permute/data/npc/mult.csv
permute/data/npc/perch.csv
permute/data/npc/rats.csv
permute/data/npc/setig.csv
permute/data/npc/urology.csv
permute/data/npc/washing_test.csv
permute/data/npc/waterfalls.csv
permute/data/npc/autofluorescence/autofl.csv
permute/data/npc/autofluorescence/drusen.csv
permute/data/npc/autofluorescence/micro.csv
permute/data/npc/autofluorescence/oct.csv
permute/data/npc/autofluorescence/pigment.csv
permute/data/npc/examples_chapters_1-4/fly.csv
permute/data/npc/examples_chapters_1-4/ipat.csv
permute/data/npc/examples_chapters_1-4/job.csv
permute/data/npc/examples_chapters_1-4/testosterone.csv
permute/data/npc/examples_chapters_1-4/worms.csv
permute/data/npc/survival/three_sample.csv
permute/data/npc/survival/three_sample_strata.csv
permute/data/npc/survival/two_sample_surv.csv
permute/data/npc/survival/two_sample_surv_strata.csv
permute/data/tests/__init__.py
permute/data/tests/test_data.py
permute/data/tests/test_macnell.py
permute/data/tests/test_nsgk.py
permute/tests/__init__.py
permute/tests/test_SPRT.py
permute/tests/test_core.py
permute/tests/test_importing.py
permute/tests/test_irr.py
permute/tests/test_ksample.py
permute/tests/test_npc.py
permute/tests/test_qa.py
permute/tests/test_stratified.py
permute/tests/test_utils.py
permute-0.2.dist-info/LICENSE
permute-0.2.dist-info/METADATA
permute-0.2.dist-info/WHEEL
permute-0.2.dist-info/top_level.txt
permute-0.2.dist-info/RECORD
