Metadata-Version: 2.1
Name: permute
Version: 0.2
Summary: Permutation tests and confidence sets for Python
Home-page: http://statlab.github.io/permute/
Author: K. Jarrod Millman, Kellie Ottoboni, and Philip B. Stark
Author-email: permute@googlegroups.com
License: BSD License
Download-URL: http://github.com/statlab/permute
Platform: UNKNOWN
Classifier: Development Status :: 3 - Alpha
Classifier: Environment :: Console
Classifier: Intended Audience :: Developers
Classifier: Intended Audience :: Science/Research
Classifier: License :: OSI Approved :: BSD License
Classifier: Programming Language :: Python
Classifier: Programming Language :: Python :: 3.7
Classifier: Programming Language :: Python :: 3.8
Classifier: Programming Language :: Python :: 3.9
Classifier: Topic :: Scientific/Engineering
Classifier: Operating System :: Microsoft :: Windows
Classifier: Operating System :: POSIX
Classifier: Operating System :: Unix
Classifier: Operating System :: MacOS
Requires-Python: >=3.7
License-File: LICENSE
Requires-Dist: numpy (>=1.20)
Requires-Dist: scipy (>=1.6)
Requires-Dist: cryptorandom (>=0.3)
